[
	{
		"enabled": true,
		"file": "game:config/traits",
		"op": "addeach",
		"path": "/-",
		"value": [
			{
				"code": "timed",
				"type": "negative",
				"attributes": {}
			},
			{
				"code": "rogue",
				"type": "positive",
				"attributes": {}
			},
			{
				"code": "trapper",
				"type": "positive",
				"attributes": {}
			}
		]
	},
	{
		"enabled": true,
		"file": "game:config/characterclasses",
		"op": "addmerge",
		"path": "/3/traits",
		"value": ["timed"]
	},
	{
		"enabled": true,
		"file": "game:config/characterclasses",
		"op": "addmerge",
		"path": "/2/traits",
		"value": ["rogue"]
	},
	{
		"enabled": true,
		"file": "game:config/characterclasses",
		"op": "addmerge",
		"path": "/1/traits",
		"value": ["trapper"]
	}
]
